arxiv_update_bot/__init__.py
arxiv_update_bot/config.example.ini
arxiv_update_bot/main.py
arxiv_update_bot-0.8.0.dist-info/entry_points.txt
arxiv_update_bot-0.8.0.dist-info/LICENSE
arxiv_update_bot-0.8.0.dist-info/WHEEL
arxiv_update_bot-0.8.0.dist-info/METADATA
arxiv_update_bot-0.8.0.dist-info/RECORD
