Metadata-Version: 2.1
Name: arxiv-update-bot
Version: 0.8.0
Summary: A bot to monitor arXiv updates
Home-page: https://github.com/nanoy42/arxiv-update-bot
License: MIT
Author: Yoann Piétri
Author-email: me@nanoy.fr
Requires-Python: >=3.7.2,<4.0
Classifier: Development Status :: 3 - Alpha
Classifier: License :: OSI Approved :: MIT License
Classifier: Programming Language :: Python :: 3
Classifier: Programming Language :: Python :: 3.8
Classifier: Programming Language :: Python :: 3.9
Classifier: Programming Language :: Python :: 3.10
Classifier: Programming Language :: Python :: 3.11
Classifier: Topic :: Scientific/Engineering
Requires-Dist: feedparser (>=6.0.8,<7.0.0)
Requires-Dist: pyTelegramBotAPI (>=3.8.1,<4.0.0)
Project-URL: Repository, https://github.com/nanoy42/arxiv-update-bot
